[
  {
    "timestamp": "2026-01-15T09:23:00.803Z",
    "date": "1/15/2026, 3:23:00 PM",
    "className": "Class 6 All in One Diamond Pack (2026)",
    "memberName": "Ismat Jahan Urmee",
    "facebookUserId": "100003680536897",
    "memberUserId": "100003680536897",
    "memberPhone": "01631709865",
    "memberTrxId": "f3ed2dc9-49ca-4134-b38c-296045ca70d4",
    "memberQA": {
      "তোমার নাম": "Ishtiaq Ahmed Zarif",
      "তোমার রেজিস্টারকৃত মোবাইল নাম্বার": "01631709865",
      "তোমার ইউনিক ট্রানজেকশন আইডি": "f3ed2dc9-49ca-4134-b38c-296045ca70d4"
    },
    "approvalStatus": "approved",
    "declineReason": null,
    "processedBy": "FB-Automation"
  }
]