[
  {
    "timestamp": "2026-01-14T20:28:09.617Z",
    "date": "1/15/2026, 2:28:09 AM",
    "className": "Class 9 Biology (2026)",
    "memberName": "Suhaib Sinan Aohin",
    "facebookUserId": "100015035884939",
    "memberUserId": "",
    "memberPhone": "",
    "memberTrxId": "",
    "memberQA": {},
    "approvalStatus": "no_answers",
    "declineReason": "প্রশ্নের উত্তর দেওয়া হয়নি",
    "processedBy": "FB-Automation"
  },
  {
    "timestamp": "2026-01-14T20:28:12.902Z",
    "date": "1/15/2026, 2:28:12 AM",
    "className": "Class 9 Biology (2026)",
    "memberName": "Arpita Dhar",
    "facebookUserId": "100067746976287",
    "memberUserId": "",
    "memberPhone": "",
    "memberTrxId": "",
    "memberQA": {},
    "approvalStatus": "no_answers",
    "declineReason": "প্রশ্নের উত্তর দেওয়া হয়নি",
    "processedBy": "FB-Automation"
  },
  {
    "timestamp": "2026-01-14T20:28:16.206Z",
    "date": "1/15/2026, 2:28:16 AM",
    "className": "Class 9 Biology (2026)",
    "memberName": "Md Asaduzzaman Akhil",
    "facebookUserId": "100007729335189",
    "memberUserId": "",
    "memberPhone": "",
    "memberTrxId": "",
    "memberQA": {
      "তোমার নাম": "Akhil"
    },
    "approvalStatus": "missing_info",
    "declineReason": "ট্রানজেকশন আইডি ও ফোন নম্বর দেওয়া হয়নি",
    "processedBy": "FB-Automation"
  },
  {
    "timestamp": "2026-01-14T20:28:19.453Z",
    "date": "1/15/2026, 2:28:19 AM",
    "className": "Class 9 Biology (2026)",
    "memberName": "Golam Sorwar Dipo",
    "facebookUserId": "100009184997585",
    "memberUserId": "",
    "memberPhone": "",
    "memberTrxId": "",
    "memberQA": {
      "তোমার নাম": "dipo"
    },
    "approvalStatus": "missing_info",
    "declineReason": "ট্রানজেকশন আইডি ও ফোন নম্বর দেওয়া হয়নি",
    "processedBy": "FB-Automation"
  },
  {
    "timestamp": "2026-01-16T10:22:55.013Z",
    "date": "1/16/2026, 4:22:55 PM",
    "className": "Class 9 Biology (2026)",
    "memberName": "Shorifa Eshita",
    "facebookUserId": "100007133804786",
    "memberUserId": "",
    "memberPhone": "",
    "memberTrxId": "",
    "memberQA": {
      "তোমার নাম": "Eshita"
    },
    "approvalStatus": "missing_info",
    "declineReason": "ট্রানজেকশন আইডি ও ফোন নম্বর দেওয়া হয়নি",
    "processedBy": "FB-Automation"
  },
  {
    "timestamp": "2026-01-16T20:34:03.160Z",
    "date": "1/17/2026, 2:34:03 AM",
    "className": "Class 9 Biology (2026)",
    "memberName": "Nava Rahman",
    "facebookUserId": "61586540428060",
    "memberUserId": "",
    "memberPhone": "01635700412",
    "memberTrxId": "d0a1c960-1421-4388-88d8-a33009e 48748",
    "memberQA": {
      "তোমার নাম": "Nidha Rahman",
      "তোমার রেজিস্টারকৃত মোবাইল নাম্বার": "01635700412",
      "তোমার ইউনিক ট্রানজেকশন আইডি": "d0a1c960-1421-4388-88d8-a33009e 48748"
    },
    "approvalStatus": "declined",
    "declineReason": "ট্রানজেকশন আইডি সঠিক নয়",
    "processedBy": "FB-Automation"
  },
  {
    "timestamp": "2026-01-17T12:34:21.498Z",
    "date": "1/17/2026, 6:34:21 PM",
    "className": "Class 9 Biology (2026)",
    "memberName": "Madhabi Purohit",
    "facebookUserId": "100026934466149",
    "memberUserId": "",
    "memberPhone": "01926825545",
    "memberTrxId": "066abf74-16b3-4d87-82f0-7eb93029e98d",
    "memberQA": {
      "তোমার নাম": "PRITOM SHARMA",
      "তোমার রেজিস্টারকৃত মোবাইল নাম্বার": "01926825545",
      "তোমার ইউনিক ট্রানজেকশন আইডি": "066abf74-16b3-4d87-82f0-7eb93029e98d"
    },
    "approvalStatus": "declined",
    "declineReason": "তুমি যে কোর্স কিনেছো, সেই কোর্সটি এই গ্রুপের জন্যে নয়",
    "processedBy": "FB-Automation"
  },
  {
    "timestamp": "2026-01-17T17:56:50.634Z",
    "date": "1/17/2026, 11:56:50 PM",
    "className": "Class 9 Biology (2026)",
    "memberName": "Kamrum Nessa",
    "facebookUserId": "61558784740784",
    "memberUserId": "",
    "memberPhone": "01830040730",
    "memberTrxId": "123456",
    "memberQA": {
      "তোমার নাম": "lmam Uddin Cishti",
      "তোমার রেজিস্টারকৃত মোবাইল নাম্বার": "01830040730",
      "তোমার ইউনিক ট্রানজেকশন আইডি": "123456"
    },
    "approvalStatus": "declined",
    "declineReason": "ট্রানজেকশন আইডি সঠিক নয়",
    "processedBy": "FB-Automation"
  },
  {
    "timestamp": "2026-01-17T17:56:56.226Z",
    "date": "1/17/2026, 11:56:56 PM",
    "className": "Class 9 Biology (2026)",
    "memberName": "Borshon Sen",
    "facebookUserId": "61554162477352",
    "memberUserId": "",
    "memberPhone": "01923783077",
    "memberTrxId": "6e3eb18b-7b28-4596-81fe-949e11e15d83",
    "memberQA": {
      "তোমার নাম": "Borshon Sen",
      "তোমার রেজিস্টারকৃত মোবাইল নাম্বার": "01923783077",
      "তোমার ইউনিক ট্রানজেকশন আইডি": "6e3eb18b-7b28-4596-81fe-949e11e15d83"
    },
    "approvalStatus": "declined",
    "declineReason": "তুমি যে কোর্স কিনেছো, সেই কোর্সটি এই গ্রুপের জন্যে নয়",
    "processedBy": "FB-Automation"
  },
  {
    "timestamp": "2026-01-19T17:40:11.838Z",
    "date": "1/19/2026, 11:40:11 PM",
    "className": "Class 9 Biology (2026)",
    "memberName": "Momotaz Begum",
    "facebookUserId": "100011447103270",
    "memberUserId": "",
    "memberPhone": "01850066689",
    "memberTrxId": "059ecaf9-87aa-4444-96cc-7c0dacf55480",
    "memberQA": {
      "তোমার নাম": "Taseen Mahmud",
      "তোমার রেজিস্টারকৃত মোবাইল নাম্বার": "01850066689",
      "তোমার ইউনিক ট্রানজেকশন আইডি": "059ecaf9-87aa-4444-96cc-7c0dacf55480"
    },
    "approvalStatus": "declined",
    "declineReason": "তুমি যে কোর্স কিনেছো, সেই কোর্সটি এই গ্রুপের জন্যে নয়",
    "processedBy": "FB-Automation"
  },
  {
    "timestamp": "2026-01-21T18:46:47.975Z",
    "date": "1/22/2026, 12:46:47 AM",
    "className": "Class 9 Biology (2026)",
    "memberName": "Borshon Sen",
    "facebookUserId": "61554162477352",
    "memberUserId": "",
    "memberPhone": "01920832421",
    "memberTrxId": "6e3eb18b-7b28-4596-81fe-949e11e15d83",
    "memberQA": {
      "তোমার নাম": "Borshon Sen",
      "তোমার রেজিস্টারকৃত মোবাইল নাম্বার": "01920832421",
      "তোমার ইউনিক ট্রানজেকশন আইডি": "6e3eb18b-7b28-4596-81fe-949e11e15d83"
    },
    "approvalStatus": "declined",
    "declineReason": "তুমি যে কোর্স কিনেছো, সেই কোর্সটি এই গ্রুপের জন্যে নয়",
    "processedBy": "FB-Automation"
  },
  {
    "timestamp": "2026-01-21T18:46:53.477Z",
    "date": "1/22/2026, 12:46:53 AM",
    "className": "Class 9 Biology (2026)",
    "memberName": "Rakib Hossen",
    "facebookUserId": "100093643984520",
    "memberUserId": "",
    "memberPhone": "01940241970",
    "memberTrxId": "218605",
    "memberQA": {
      "তোমার নাম": "Md Rakib Hossen",
      "তোমার রেজিস্টারকৃত মোবাইল নাম্বার": "01940241970",
      "তোমার ইউনিক ট্রানজেকশন আইডি": "218605"
    },
    "approvalStatus": "declined",
    "declineReason": "ট্রানজেকশন আইডি সঠিক নয়",
    "processedBy": "FB-Automation"
  },
  {
    "timestamp": "2026-01-22T08:50:58.116Z",
    "date": "1/22/2026, 2:50:58 PM",
    "className": "Class 9 Biology (2026)",
    "memberName": "Abu Bakar Siddik",
    "facebookUserId": "61586956346842",
    "memberUserId": "",
    "memberPhone": "01725556855",
    "memberTrxId": "790072c6-74ab-4811-9fd9-badc8ec7924a",
    "memberQA": {
      "তোমার নাম": "Abu Bakar Siddik",
      "তোমার রেজিস্টারকৃত মোবাইল নাম্বার": "01725556855",
      "তোমার ইউনিক ট্রানজেকশন আইডি": "790072c6-74ab-4811-9fd9-badc8ec7924a"
    },
    "approvalStatus": "declined",
    "declineReason": "তুমি যে কোর্স কিনেছো, সেই কোর্সটি এই গ্রুপের জন্যে নয়",
    "processedBy": "FB-Automation"
  },
  {
    "timestamp": "2026-01-24T03:34:57.977Z",
    "date": "1/24/2026, 9:34:57 AM",
    "className": "Class 9 Biology (2026)",
    "memberName": "Ore Wa Trihan",
    "facebookUserId": "61582341775440",
    "memberUserId": "",
    "memberPhone": "01829608886",
    "memberTrxId": "",
    "memberQA": {
      "তোমার নাম": "Trihan",
      "তোমার রেজিস্টারকৃত মোবাইল নাম্বার": "01829608886"
    },
    "approvalStatus": "missing_info",
    "declineReason": "ট্রানজেকশন আইডি দেওয়া হয়নি",
    "processedBy": "FB-Automation"
  },
  {
    "timestamp": "2026-01-24T03:35:03.475Z",
    "date": "1/24/2026, 9:35:03 AM",
    "className": "Class 9 Biology (2026)",
    "memberName": "Abu Bakar Siddik",
    "facebookUserId": "61586956346842",
    "memberUserId": "",
    "memberPhone": "01725556855",
    "memberTrxId": "790072c6-74ab-4811-9fd9-badc8ec7924a",
    "memberQA": {
      "তোমার নাম": "Abu Bakar Siddik",
      "তোমার রেজিস্টারকৃত মোবাইল নাম্বার": "01725556855",
      "তোমার ইউনিক ট্রানজেকশন আইডি": "790072c6-74ab-4811-9fd9-badc8ec7924a"
    },
    "approvalStatus": "declined",
    "declineReason": "তুমি যে কোর্স কিনেছো, সেই কোর্সটি এই গ্রুপের জন্যে নয়",
    "processedBy": "FB-Automation"
  },
  {
    "timestamp": "2026-01-24T03:35:09.015Z",
    "date": "1/24/2026, 9:35:09 AM",
    "className": "Class 9 Biology (2026)",
    "memberName": "Fazilatun Nessa",
    "facebookUserId": "61550697530495",
    "memberUserId": "",
    "memberPhone": "01830040730",
    "memberTrxId": "123456",
    "memberQA": {
      "তোমার নাম": "Imam Uddin cishti",
      "তোমার রেজিস্টারকৃত মোবাইল নাম্বার": "01830040730",
      "তোমার ইউনিক ট্রানজেকশন আইডি": "123456"
    },
    "approvalStatus": "declined",
    "declineReason": "ট্রানজেকশন আইডি সঠিক নয়",
    "processedBy": "FB-Automation"
  },
  {
    "timestamp": "2026-01-24T03:35:25.105Z",
    "date": "1/24/2026, 9:35:25 AM",
    "className": "Class 9 Biology (2026)",
    "memberName": "Md Mohidul Hasan",
    "facebookUserId": "100060689075452",
    "memberUserId": "",
    "memberPhone": "",
    "memberTrxId": "",
    "memberQA": {
      "তোমার নাম": "Nnk"
    },
    "approvalStatus": "missing_info",
    "declineReason": "ট্রানজেকশন আইডি ও ফোন নম্বর দেওয়া হয়নি",
    "processedBy": "FB-Automation"
  },
  {
    "timestamp": "2026-01-24T03:35:30.572Z",
    "date": "1/24/2026, 9:35:30 AM",
    "className": "Class 9 Biology (2026)",
    "memberName": "Mottasim Billah",
    "facebookUserId": "61583632805943",
    "memberUserId": "",
    "memberPhone": "01722460662",
    "memberTrxId": "k98e2f781d2et78fcxhhff6a",
    "memberQA": {
      "তোমার নাম": "Abdullah mahir",
      "তোমার রেজিস্টারকৃত মোবাইল নাম্বার": "01722460662",
      "তোমার ইউনিক ট্রানজেকশন আইডি": "k98e2f781d2et78fcxhhff6a"
    },
    "approvalStatus": "declined",
    "declineReason": "ট্রানজেকশন আইডি সঠিক নয়",
    "processedBy": "FB-Automation"
  },
  {
    "timestamp": "2026-01-24T03:35:35.873Z",
    "date": "1/24/2026, 9:35:35 AM",
    "className": "Class 9 Biology (2026)",
    "memberName": "Noman Shohan",
    "facebookUserId": "100081694303347",
    "memberUserId": "",
    "memberPhone": "",
    "memberTrxId": "",
    "memberQA": {
      "তোমার নাম": "Noman"
    },
    "approvalStatus": "missing_info",
    "declineReason": "ট্রানজেকশন আইডি ও ফোন নম্বর দেওয়া হয়নি",
    "processedBy": "FB-Automation"
  },
  {
    "timestamp": "2026-01-24T03:35:41.368Z",
    "date": "1/24/2026, 9:35:41 AM",
    "className": "Class 9 Biology (2026)",
    "memberName": "Afroza Bulbul",
    "facebookUserId": "61553848260032",
    "memberUserId": "",
    "memberPhone": "01912949470",
    "memberTrxId": "TrxID\n\nDAN7EHGR21",
    "memberQA": {
      "তোমার নাম": "Md rimon rana",
      "তোমার রেজিস্টারকৃত মোবাইল নাম্বার": "01912949470",
      "তোমার ইউনিক ট্রানজেকশন আইডি": "TrxID\n\nDAN7EHGR21"
    },
    "approvalStatus": "declined",
    "declineReason": "ট্রানজেকশন আইডি সঠিক নয়",
    "processedBy": "FB-Automation"
  },
  {
    "timestamp": "2026-01-24T03:35:57.345Z",
    "date": "1/24/2026, 9:35:57 AM",
    "className": "Class 9 Biology (2026)",
    "memberName": "Shithil Shanto",
    "facebookUserId": "61559871805648",
    "memberUserId": "",
    "memberPhone": "01967588449",
    "memberTrxId": "",
    "memberQA": {
      "তোমার নাম": "Shanto",
      "তোমার রেজিস্টারকৃত মোবাইল নাম্বার": "01967588449"
    },
    "approvalStatus": "missing_info",
    "declineReason": "ট্রানজেকশন আইডি দেওয়া হয়নি",
    "processedBy": "FB-Automation"
  },
  {
    "timestamp": "2026-01-24T03:36:13.566Z",
    "date": "1/24/2026, 9:36:13 AM",
    "className": "Class 9 Biology (2026)",
    "memberName": "H.R. Alif",
    "facebookUserId": "61577309045588",
    "memberUserId": "",
    "memberPhone": "01876341024",
    "memberTrxId": "hamderabbialif1@gmail.com",
    "memberQA": {
      "তোমার নাম": "Md Hamde Rabbi Alif",
      "তোমার রেজিস্টারকৃত মোবাইল নাম্বার": "01876341024",
      "তোমার ইউনিক ট্রানজেকশন আইডি": "hamderabbialif1@gmail.com"
    },
    "approvalStatus": "declined",
    "declineReason": "ট্রানজেকশন আইডি সঠিক নয়",
    "processedBy": "FB-Automation"
  },
  {
    "timestamp": "2026-01-24T13:45:33.054Z",
    "date": "1/24/2026, 7:45:33 PM",
    "className": "Class 9 Biology (2026)",
    "memberName": "H.R. Alif",
    "facebookUserId": "61577309045588",
    "memberUserId": "",
    "memberPhone": "01876341024",
    "memberTrxId": "hamderabbialif1@gmail.com",
    "memberQA": {
      "তোমার নাম": "Md Hamde Rabbi Alif",
      "তোমার রেজিস্টারকৃত মোবাইল নাম্বার": "01876341024",
      "তোমার ইউনিক ট্রানজেকশন আইডি": "hamderabbialif1@gmail.com"
    },
    "approvalStatus": "declined",
    "declineReason": "ট্রানজেকশন আইডি সঠিক নয়",
    "processedBy": "FB-Automation"
  },
  {
    "timestamp": "2026-01-24T13:45:38.526Z",
    "date": "1/24/2026, 7:45:38 PM",
    "className": "Class 9 Biology (2026)",
    "memberName": "Afroza Bulbul",
    "facebookUserId": "61553848260032",
    "memberUserId": "",
    "memberPhone": "01912949470",
    "memberTrxId": "TrxID\n\nDAN7EHGR21",
    "memberQA": {
      "তোমার নাম": "Md rimon rana",
      "তোমার রেজিস্টারকৃত মোবাইল নাম্বার": "01912949470",
      "তোমার ইউনিক ট্রানজেকশন আইডি": "TrxID\n\nDAN7EHGR21"
    },
    "approvalStatus": "declined",
    "declineReason": "ট্রানজেকশন আইডি সঠিক নয়",
    "processedBy": "FB-Automation"
  },
  {
    "timestamp": "2026-01-24T13:45:43.815Z",
    "date": "1/24/2026, 7:45:43 PM",
    "className": "Class 9 Biology (2026)",
    "memberName": "Murshida Jahan Mafi",
    "facebookUserId": "61573600689870",
    "memberUserId": "",
    "memberPhone": "",
    "memberTrxId": "",
    "memberQA": {
      "তোমার নাম": "Murshida jahan mafi"
    },
    "approvalStatus": "missing_info",
    "declineReason": "ট্রানজেকশন আইডি ও ফোন নম্বর দেওয়া হয়নি",
    "processedBy": "FB-Automation"
  },
  {
    "timestamp": "2026-01-26T10:38:46.579Z",
    "date": "1/26/2026, 4:38:46 PM",
    "className": "Class 9 Biology (2026)",
    "memberName": "Afroza Bulbul",
    "facebookUserId": "61553848260032",
    "memberUserId": "",
    "memberPhone": "01912949470",
    "memberTrxId": "9c-fe9e-4901-bc06-38c3e51681fO",
    "memberQA": {
      "তোমার নাম": "Md Rimon rana",
      "তোমার রেজিস্টারকৃত মোবাইল নাম্বার": "01912949470",
      "তোমার ইউনিক ট্রানজেকশন আইডি": "9c-fe9e-4901-bc06-38c3e51681fO"
    },
    "approvalStatus": "declined",
    "declineReason": "ট্রানজেকশন আইডি সঠিক নয়",
    "processedBy": "FB-Automation"
  },
  {
    "timestamp": "2026-02-07T07:44:31.004Z",
    "date": "2/7/2026, 1:44:31 PM",
    "className": "Class 9 Biology (2026)",
    "memberName": "R K Babu",
    "facebookUserId": "100073096607396",
    "memberUserId": "",
    "memberPhone": "RSL",
    "memberTrxId": "RSL",
    "memberQA": {
      "তোমার নাম": "RSL",
      "তোমার রেজিস্টারকৃত মোবাইল নাম্বার": "RSL",
      "তোমার ইউনিক ট্রানজেকশন আইডি": "RSL"
    },
    "approvalStatus": "declined",
    "declineReason": "ট্রানজেকশন আইডি সঠিক নয়",
    "processedBy": "FB-Automation"
  },
  {
    "timestamp": "2026-02-07T07:44:57.871Z",
    "date": "2/7/2026, 1:44:57 PM",
    "className": "Class 9 Biology (2026)",
    "memberName": "Hossian Muhammad Samiullah",
    "facebookUserId": "100055840584429",
    "memberUserId": "",
    "memberPhone": "01620153076",
    "memberTrxId": "b9061d3f-1793-4be1-8d67-6521bf1fbbba",
    "memberQA": {
      "তোমার নাম": "Hossian Muhammad Samiullah",
      "তোমার রেজিস্টারকৃত মোবাইল নাম্বার": "01620153076",
      "তোমার ইউনিক ট্রানজেকশন আইডি": "b9061d3f-1793-4be1-8d67-6521bf1fbbba"
    },
    "approvalStatus": "declined",
    "declineReason": "এই ট্রানজেকশন আইডি একবার ব্যবহৃত হয়েছে, একটি ট্রানজেকশন আইডি ব্যবহার করে একবারই গ্রুপে জয়েন হতে পারবে",
    "processedBy": "FB-Automation"
  },
  {
    "timestamp": "2026-02-07T07:45:03.215Z",
    "date": "2/7/2026, 1:45:03 PM",
    "className": "Class 9 Biology (2026)",
    "memberName": "Masuda Begum",
    "facebookUserId": "100070897155700",
    "memberUserId": "",
    "memberPhone": "",
    "memberTrxId": "",
    "memberQA": {
      "তোমার নাম": "naima"
    },
    "approvalStatus": "missing_info",
    "declineReason": "ট্রানজেকশন আইডি ও ফোন নম্বর দেওয়া হয়নি",
    "processedBy": "FB-Automation"
  },
  {
    "timestamp": "2026-02-09T18:47:54.561Z",
    "date": "2/10/2026, 12:47:54 AM",
    "className": "Class 9 Biology (2026)",
    "memberName": "Shilpi Akter",
    "facebookUserId": "61554397785612",
    "memberUserId": "",
    "memberPhone": "01715562636",
    "memberTrxId": "0cefd211-7afc-42fa-bcb8-b460f1d9b266",
    "memberQA": {
      "তোমার নাম": "MD SAZID MIA",
      "তোমার রেজিস্টারকৃত মোবাইল নাম্বার": "01715562636",
      "তোমার ইউনিক ট্রানজেকশন আইডি": "0cefd211-7afc-42fa-bcb8-b460f1d9b266"
    },
    "approvalStatus": "declined",
    "declineReason": "তুমি যে কোর্স কিনেছো, সেই কোর্সটি এই গ্রুপের জন্যে নয়",
    "processedBy": "FB-Automation"
  },
  {
    "timestamp": "2026-02-09T18:48:00.031Z",
    "date": "2/10/2026, 12:48:00 AM",
    "className": "Class 9 Biology (2026)",
    "memberName": "Sealina Akther",
    "facebookUserId": "100012379387821",
    "memberUserId": "",
    "memberPhone": "01404916648",
    "memberTrxId": "01404916648",
    "memberQA": {
      "তোমার নাম": "Ayesha Aktar",
      "তোমার রেজিস্টারকৃত মোবাইল নাম্বার": "01404916648",
      "তোমার ইউনিক ট্রানজেকশন আইডি": "01404916648"
    },
    "approvalStatus": "declined",
    "declineReason": "ট্রানজেকশন আইডি সঠিক নয়",
    "processedBy": "FB-Automation"
  },
  {
    "timestamp": "2026-02-09T18:48:05.510Z",
    "date": "2/10/2026, 12:48:05 AM",
    "className": "Class 9 Biology (2026)",
    "memberName": "Hossian Muhammad Samiullah",
    "facebookUserId": "100055840584429",
    "memberUserId": "",
    "memberPhone": "01620153076",
    "memberTrxId": "b9061d3f-1793-4be1-8d67-6521bf1fbbba",
    "memberQA": {
      "তোমার নাম": "Hossian Muhammad Samiullah",
      "তোমার রেজিস্টারকৃত মোবাইল নাম্বার": "01620153076",
      "তোমার ইউনিক ট্রানজেকশন আইডি": "b9061d3f-1793-4be1-8d67-6521bf1fbbba"
    },
    "approvalStatus": "declined",
    "declineReason": "এই ট্রানজেকশন আইডি একবার ব্যবহৃত হয়েছে, একটি ট্রানজেকশন আইডি ব্যবহার করে একবারই গ্রুপে জয়েন হতে পারবে",
    "processedBy": "FB-Automation"
  },
  {
    "timestamp": "2026-02-15T09:08:31.938Z",
    "date": "2/15/2026, 3:08:31 PM",
    "className": "Class 9 Biology (2026)",
    "memberName": "Saiful Islam",
    "facebookUserId": "100003765366013",
    "memberUserId": "",
    "memberPhone": "01708169807",
    "memberTrxId": "প্রিয় শিক্ষার্থী, তোমার একাডেমিক প্রোগ্রাম ২০২৬ টি পারচেজ সফল হয়েছে। তোমার ইনভয়েস লিঙ্কঃ https://www.acsfutureschool.com/purchase-flow/payment-success?paymentId=2f04c700-b348-4b62-b80e-5ded64496918 \n\nকোর্সের প্রাইভেট গ্রুপ এ জয়েন করতে,\n\n                ১। গ্রুপ লিঙ্কঃ https://www.facebook.com/share/g/1T8K2fVRww/\n\n                ২। এক্সেস কোডঃ 2f04c700-b348-4b62-b80e-5ded64496918\n\n                          \nতোমার গিফট  আমরা ১০-১৫ জানুয়ারি এর মধ্যে নির্দিষ্ট ঠিকানায় পাঠিয়ে দিবো।\n\n\nতুমি চাইলে তোমার বন্ধুকে রেফার করে জিতে নিতে পারো একটি আকর্ষণীয় হুডি! রেফার লিংক: https://acsfutureschool.com/claim-hoodie",
    "memberQA": {
      "তোমার নাম": "Raiyan",
      "তোমার রেজিস্টারকৃত মোবাইল নাম্বার": "01708169807",
      "তোমার ইউনিক ট্রানজেকশন আইডি": "প্রিয় শিক্ষার্থী, তোমার একাডেমিক প্রোগ্রাম ২০২৬ টি পারচেজ সফল হয়েছে। তোমার ইনভয়েস লিঙ্কঃ https://www.acsfutureschool.com/purchase-flow/payment-success?paymentId=2f04c700-b348-4b62-b80e-5ded64496918 \n\nকোর্সের প্রাইভেট গ্রুপ এ জয়েন করতে,\n\n                ১। গ্রুপ লিঙ্কঃ https://www.facebook.com/share/g/1T8K2fVRww/\n\n                ২। এক্সেস কোডঃ 2f04c700-b348-4b62-b80e-5ded64496918\n\n                          \nতোমার গিফট  আমরা ১০-১৫ জানুয়ারি এর মধ্যে নির্দিষ্ট ঠিকানায় পাঠিয়ে দিবো।\n\n\nতুমি চাইলে তোমার বন্ধুকে রেফার করে জিতে নিতে পারো একটি আকর্ষণীয় হুডি! রেফার লিংক: https://acsfutureschool.com/claim-hoodie"
    },
    "approvalStatus": "declined",
    "declineReason": "ট্রানজেকশন আইডি সঠিক নয়",
    "processedBy": "FB-Automation"
  }
]